Workbook

Sheet KPIs produit
A1: KPI | B1: Definition exacte | C1: Cible
A2: Scans / jour | B2: Nombre total de scans produits reussis, tous utilisateurs confondus, agrege sur 24h. (En partant du principe que 2 scans par jour par utilisateur soient faits) | C2: ='Hypothèses de coûts'!C2*2 -> 10000
A3: Taux d'activation (J+7) | B3: Part des comptes crees ayant realise >=3 scans ET consulte >=1 fiche substitution, mesuree a J+7 | C3: 0.7
A4: Retention à 30 jours | B4: Part des utilisateurs actifs a J0 qui reutilisent l'application a J30 | C4: 0.6
A5: Taux de substitution acceptee | B5: Part des propositions de substitution affichees qui sont acceptees (clic + usage), sur une periode donnee. | C5: 0.4
A6: Cout par requete assistant | B6: Cout moyen en tokens LLM d'une conversation assistant = cout total tokens du mois / nb de conversations du mois (cf. onglet Hypotheses_couts). | C6: 0.02
A7: Taux de conversion premium | B7: Part des utilisateurs actifs freemium qui souscrivent a l'offre premium, mesuree sur une fenetre glissante de 3 semaines. | C7: 0.1
A8: Conversations avec l'assistant / utilisateur | B8: Nombre moyen de conversations avec l'assistant par utilisateur actif et par mois, mesure collectivement (pas de suivi individuel) | C8: 3

Sheet Hypothèses de coûts
A1: Hypothèse | B1: Scénario pessimiste | C1: Scénario central | D1: Scénario optimiste
A2: Utilisateurs actifs mensuels | B2: 1000 | C2: 5000 | D2: 20000
A3: Taux de conversion premium | B3: 2 | C3: 3 | D3: 5
A4: Nombre d'utilisateurs premium | B4: 20 | C4: 150 | D4: 1000
A5: Prix abonnement premium / mois | B5: 1.45 | C5: 2.99 | D5: 5.99
A6: Chiffre d'affaires mensuel | B6: =B4*B5 -> 29 | C6: =C4*C5 -> 448.5 | D6: =D4*D5 -> 5990
A7: Chiffre d'affaires annuel | B7: =B6*12 -> 348 | C7: =C6*12 -> 5382 | D7: =D6*12 -> 71880

Sheet Hypothèses de revenus
B1: Scénario pessimiste | C1: Scénario central | D1: Scénario optimiste
A2: Utilisateurs actifs | B2: ='Hypothèses de coûts'!B2 -> 1000 | C2: ='Hypothèses de coûts'!C2 -> 5000 | D2: ='Hypothèses de coûts'!D2 -> 20000
A3: Utilisateurs premium | B3: ='Hypothèses de coûts'!B4 -> 20 | C3: ='Hypothèses de coûts'!C4 -> 150 | D3: ='Hypothèses de coûts'!D4 -> 1000
A4: Prix abonnement premium / mois | B4: 1.45 | C4: 2.99 | D4: 5.99
A5: Revenu premium mensuel (EUR) | B5: =B4*B3 -> 29 | C5: =C4*C3 -> 448.5 | D5: =D4*D3 -> 5990

Sheet Calcul de ROI
A1: Hypothèse/KPI | B1: Hypothèse pessimiste | C1: Hypothèse centrale | D1: Hypothèse optimiste
A2: Utilisateurs actifs mensuels | B2: ='Hypothèses de coûts'!B2 -> 1000 | C2: ='Hypothèses de coûts'!C2 -> 5000 | D2: ='Hypothèses de coûts'!D2 -> 20000
A3: Taux de conversion premium | B3: ='Hypothèses de coûts'!B3 -> 2 | C3: ='Hypothèses de coûts'!C3 -> 3 | D3: ='Hypothèses de coûts'!D3 -> 5
A4: Utilisateurs premium | B4: ='Hypothèses de coûts'!B4 -> 20 | C4: ='Hypothèses de coûts'!C4 -> 150 | D4: ='Hypothèses de coûts'!D4 -> 1000
A5: Prix premium / mois (€) | B5: ='Hypothèses de coûts'!B5 -> 1.45 | C5: ='Hypothèses de coûts'!C5 -> 2.99 | D5: ='Hypothèses de coûts'!D5 -> 5.99
A6: Revenu premium mensuel | B6: =B4*B5 -> 29 | C6: =C4*C5 -> 448.5 | D6: =D4*D5 -> 5990
A7: Revenu annuel | B7: =B6*12 -> 348 | C7: =C6*12 -> 5382 | D7: =D6*12 -> 71880
A8: Jours-hommes estimés (350€ TJM) | B8: 25 | C8: 18 | D8: 12
A9: Coûts développement / an | B9: 8750 | C9: 6300 | D9: 4200
A10: Coûts infra / an | B10: 300 | C10: 700 | D10: 1750
A11: Coûts IA / API / an | B11: 50 | C11: 250 | D11: 1000
A12: Coûts totaux annuels | B12: =B10+B11+B9 -> 9100 | C12: =C10+C11+C9 -> 7250 | D12: =D10+D11+D9 -> 6950
A13: Résultat annuel | B13: =B7-B12 -> -8752 | C13: =C7-C12 -> -1868 | D13: =D7-D12 -> 64930
A14: ROI | B14: =(B13/B12) -> -0.96175824 | C14: =(C13/C12) -> -0.25765517 | D14: =(D13/D12) -> 9.342446

Sheet Adoption
A1: KPI | B1: Definition exacte | C1: Seuil d'alerte | D1: Plan de relance
A2: Retention à 30 jours | B2: Proportion des utilisateurs ayant commencé à utiliser NutriScope qui réutilisent l'application 30 jours après leur première utilisation, mesurée sur chaque cohorte mensuelle. | C2: < 35% | D2: Analyser les causes de non-rétention et lancer des actions de relance/communication sur les fonctionnalités les plus pertinentes.
A3: Conversion premium | B3: Proportion d'utilisateurs freemium qui souscrivent à l'offre premium, mesurée sur une fenêtre glissante de 3 semaines. | C3: < 3% | D3: Analyser les freins à la conversion, recueillir les retours des utilisateurs freemium et ajuster la communication et les fonctionnalités de l'offre premium.
A4: Substitution acceptée | B4: Proportion de propositions de produits de substitution acceptées par les utilisateurs, sur une période donnée. | C4: < 15% | D4: Analyser les produits de substitution les moins acceptés et recueillir les retours des utilisateurs pour améliorer la pertinence des recommandations.
A5: Conversations avec l'assistant / utilisateur | B5: Nombre moyen de conversations avec l'assistant par utilisateur actif et par mois, mesuré collectivement (pas de suivi individuel). | C5: < 1 conversation par utilisateur actif et par mois | D5: Analyser la satisfaction des utilisateurs sur les réponses de l'assistant et améliorer les réponses sur les points identifiés comme insatisfaisants.
